consdata/__init__.py
consdata/__main__.py
consdata/config.py
consdata/sample.py
consdata/utils.py
consdata-0.0.1.dist-info/WHEEL
consdata-0.0.1.dist-info/METADATA
consdata-0.0.1.dist-info/RECORD
