Metadata-Version: 2.4
Name: consdata
Version: 0.0.1
Summary: Utility to fetch constituents data from various sources
Keywords: utility
Author: Furechan
Author-email: Furechan <furechan@xsmail.com>
License-Expression: MIT
Classifier: Development Status :: 1 - Planning
Classifier: Programming Language :: Python :: 3
Classifier: License :: OSI Approved :: MIT License
Classifier: Operating System :: OS Independent
Requires-Dist: click
Requires-Dist: pandas
Requires-Dist: pyarrow
Requires-Dist: cloudpathlib
Requires-Dist: s3fs>=2024.0.0 ; extra == 's3'
Requires-Python: >=3.9
Provides-Extra: s3
